MANIFEST.in
README.txt
setup.py
c2/__init__.py
c2.backup.s3.egg-info/PKG-INFO
c2.backup.s3.egg-info/SOURCES.txt
c2.backup.s3.egg-info/dependency_links.txt
c2.backup.s3.egg-info/entry_points.txt
c2.backup.s3.egg-info/namespace_packages.txt
c2.backup.s3.egg-info/requires.txt
c2.backup.s3.egg-info/top_level.txt
c2/backup/__init__.py
c2/backup/s3/__init__.py
c2/backup/s3/config.py
c2/backup/s3/listing.py
c2/backup/s3/main.py
c2/backup/s3/upload.py
docs/HISTORY.txt