Metadata-Version: 1.1
Name: c2.backup.s3
Version: 1.0a4
Summary: This package supports back up files from local dir to S3 bucket
Home-page: https://bitbucket.org/cmscom/c2.backup.s3
Author: Manabu TERADA
Author-email: terada@cmscom.jp
License: GPL
Platform: UNKNOWN
Classifier: Programming Language :: Python
